{
  "杭州_日日抽锦鲤": "hecaiyun_ac1",
  "杭州_月月领流量": "hecaiyun_ac1",
  "广西_送豪礼": "caiyunActConePage",
  "湖南_新三重礼": "caiyunActivePage",
  "湖北_小程序": "hecaiyunPage",
  "江西_三重礼": "jxspring",
  "江西_小程序": "caiyunActConePage",
  "江西_TV端登录有礼": "hecaiyunPage",
  "江西_邀请码": "caiyunActivePage",
  "江西邀请码": "caiyunActivePage",
  "广东_小程序": "caiyunActivePage",
  "广东__小程序": "caiyunActivePage",
  "广东_邀请码": "caiyunActivePage",
  "广东邀请码": "caiyunActivePage",
  "湖南_发现精彩": "caiyunMcloudActive",
  "湖南_排位赛": "caiyunActivePage",
  "湖南_三重礼": "caiyunActConePage",
  "湖南_邀新有礼": "caiyunActivePage",
  "湖南_上传有礼": "caiyunMcloudActive",
  "江苏_小程序": "caiyunMcloudActive",
  "江苏_壕礼嗨不停": "caiyunActivePage",
  "江苏_云笔记": "caiyunActivity",
  "江苏_APP下载三合一": "clientDL",
  "江苏_短视频大赛": "hecaiyunPage",
  "江苏_保险箱": "hecaiyunPage",
  "江苏_自动备份领好礼": "cyActive",
  "湖南_转存有礼": "cyActive",
  "河南_豪礼享不停": "hecaiyunPage",
  "河南_6GB流量限时领": "caiyunActivePage",
  "山东_转存分享赢好礼": "caiyunMcloudActive",
  "河北_冰雪运动会": "CaiYunActive",
  "安徽_网盘小程序": "caiyunMcloudActive",
  "安徽_新好礼三重奏": "caiyunMcloudActive",
  "安徽_新三重礼": "caiyunMcloudActive",
  "安徽_转存分享有礼": "caiyunActivity",
  "安徽_转存分享赢好礼": "caiyunActivity",
  "安徽_好礼三重奏": "hecaiyun_ac1",
  "福建_流量月月领": "fjllmfl",
  "福建_PC推荐码": "caiyunActivity",
  "上海_三重礼": "caiyunActivePage",
  "上海_ 三重礼": "caiyunActivePage",
  "上海_邀请码": "caiyunActivePage",
  "上海邀请码": "caiyunActivePage",
  "北京_邀请码": "caiyunActivePage",
  "北京邀请码": "caiyunActivePage",
  "山西_上传赢好礼": "caiyunActConePage",
  "山西_邀请码": "caiyunActivePage",
  "山西邀请码": "caiyunActivePage",
  "宁夏_话费月月盘": "hecaiyunPage",
  "新疆_三重礼": "xjPrizeActive",
  "青海_登录有礼": "CaiYunActive",
  "陕西_二重礼": "caiyunActivePage",
  "陕西_月用月有礼": "caiyunActivity",
  "甘肃_小程序": "CaiYunActive",
  "甘肃_邀请码": "caiyunActivePage",
  "甘肃邀请码": "caiyunActivePage",
  "贵州_上传邀请享豪礼": "CaiYunActive",
  "贵州_好礼三重奏": "CaiYunActive",
  "重庆_重庆资产账单": "caiyunBill",
  "辽宁_好礼三重奏": "caiyunMcloudActive",
  "辽宁_三重奏": "caiyunMcloudActive",
  "吉林_月月瓜分": "hecaiyunPage",
  "吉林_双重礼": "hecaiyunPage",
  "黑龙江_越用越有礼": "hljgift",
  "广西_邀请码": "caiyunActivePage",
  "广西邀请码": "caiyunActivePage",
  "杭州_盲盒抽奖": "caiyunMcloudActive",
  "杭州_分享赢百元话费": "caiyunActConePage",
  "浙江_家庭云": "caiyunMcloudActive",
  "海南_送话费": "hecaiyunPage",
  "海南_上传文件领话费": "hnUpLoad",
  "江西_推荐官": "caiyunActivity",
  "江西_云笔记": "hecaiyunPage",
  "江西_订购页": "jiangxiorder",
  "广东订购页_全套餐": "caiyunorder",
  "广东_订购页_全套餐": "caiyunorder",
  "广东订购页_4T": "gdvipmonthorder",
  "广东订购页_1T+5G": "gd1000G5G",
  "广东订购页_1000G+5GB": "gd1000G5G",
  "广东订购页_4T+10G": "gd4T10G",
  "广东订购页_400G+2GB": "gd400G2G",
  "广东订购页_400G +2GB": "gd400G2G",
  "广东订购页_200G+1GB": "gd4T2G",
  "广东_订购页_200G+1GB": "gd4T2G",
  "广东_订购页_4T+5GB": "gd4T5G",
  "广东_真题会员订购页": "cyActive",
  "广东_真题订购页": "cyActive",
  "广东_分享享流量": "caiyunMcloudActive",
  "广东_三重礼": "gdxiarinew",
  "广东_好礼三重奏": "gdxiarinew",
  "分省中间页_个人云首页": "caiyunMcloudActive",
  "分省中间页_我的": "caiyunMcloudActive",
  "分省中间页_发现广场": "caiyunMcloudActive",
  "分省中间页_我的卡包": "caiyunMcloudActive",
  "分省通用中间页_话费账单": "caiyunMcloudActive",
  "安徽_话费账单中间页": "caiyunMcloudActive",
  "话费账单_端外页": "caiyunMcloudActive",
  "重庆_小程序账单端外页": "caiyunMcloudActive",
  "重庆_邀请码": "caiyunActivePage",
  "重庆邀请码": "caiyunActivePage",
  "重庆_移动crm链接": "caiyunActivityCloud",
  "辽宁_邀请码": "caiyunActivePage",
  "河南_小程序": "caiyunActivePage",
  "辽宁邀请码": "caiyunActivePage",
  "辽宁短信场景使用": "clientDL",
  "广西短信场景使用": "clientDL",
  "山西_0元领30G": "caiyunOfficialAccount",
  "山西_0元30G": "caiyunOfficialAccount",
  "全国_在线账单": "caiyunMcloudActive",
  "山西_小程序发现页面": "hecaiyunPage",
  "陕西_转存赢好礼": "hecaiyunPage",
  "陕西_线下_转存赢好礼": "hecaiyunPage",
  "全国_内部员工权益": "caiyunEventPage",
  "湖北_三重礼": "hecaiyunPage",
  "湖北_照片直播": "caiyunMcloudActive",
  "湖北_上传有礼": "caiyunMcloudActive",
  "湖北_校园打卡": "caiyunActivity",
  "湖北_摄影大赛": "cyActive",
  "湖北_双重礼": "caiyunActivePage",
  "湖北_TV端登录有礼": "caiyunActivePage",
  "天津_开年赢好礼": "hecaiyunPage",
  "天津_开年迎好礼": "hecaiyunPage",
  "天津_狂欢季": "hecaiyunPage",
  "天津_感恩回馈双重奏": "CaiYunActive",
  "广东_登录云盘送话费": "taskTemplate",
  "广东_登录免流方案": "taskTemplate",
  "广东模板": "taskTemplate",
  "分省中间页_我的应用收藏": "caiyunMcloudActive",
  "广西_体验有礼": "caiyunActivity",
  "湖北_校园毕业季": "caiyunActivity",
  "北京_分享享流量": "caiyunMcloudActive",
  "江苏_功能体验三合一": "cyActive",
  "江苏_功能体验三重礼": "cyActive",
  "江苏_马拉松": "caiyunMcloudActive",
  "山东_亲情圈": "caiyunMcloudActive",
  "西藏_领好礼": "hecaiyunPage",
  "西藏_ 月月领流量": "caiyunMcloudActive",
  "福建_成绩查询中间页": "caiyunMcloudActive",
  "吉林_邀请有礼": "cyActive",
  "新疆_签到打卡": "caiyunMcloudActive",
  "新疆_助力得话费": "caiyunMcloudActive",
  "河南_备份有礼": "hecaiyunPage",
  "河南_邀请有礼": "hecaiyunPage",
  "上海_邀请好友订会员": "cyActive",
  "上海_TV登录有礼": "caiyunMcloudActive",
  "上海_TV登陆有礼": "caiyunMcloudActive",
  "河南_转存有礼": "hecaiyunPage",
  "陕西_自动备份": "caiyunMcloudActive",
  "陕西_分享有好礼": "caiyunMcloudActive",
  "河南_上传有礼": "hecaiyunPage",
  "河南_狂欢季": "hnhnyact",
  "山西_新TV登录有礼": "",
  "山西_TV登录有礼": "",
  "上海_新TV登录有礼": "",
  "福建_TV登录有礼": "",
  "山东_三合一": "clientDL",
  "广东_三合一": "clientDL",
  "广东_停车订购页": "caiyunMcloudActive",
  "广东_畅影订购页": "caiyunMcloudActive",
  "湖北_云笔记": "caiyunMcloudActive",
  "四川_登录有礼": "hecaiyunPage",
  "四川_零元会员订购": "hecaiyunPage",
  "天津_礼享生活": "hecaiyunPage",
  "山西_登录PC有礼": "hecaiyunPage",
  "山西_自动备份有礼": "caiyunMcloudActive",
  "浙江_亚运": "caiyunMcloudActive",
  "湖北_登录有礼": "caiyunMcloudActive",
  "辽宁_邮箱账单": "caiyunMcloudActive",
  "天津_豪礼享不停": "caiyunMcloudActive",
  "宁夏_上传有礼": "yunpage",
  "甘肃_上传好礼": "yunpage",
  "青海_云盘": "yunpage",
  "宁夏_H5登录": "yunpage",
  "重庆_资产账单": "caiyunBill",
  "湖北_分享有礼": "cloudDisk",
  "湖北_新分享有礼": "cloudDisk",
  "湖南_活跃有礼": "cloudDisk",
  "广西_H5登录有礼": "cloudDisk",
  "安徽_答题赢好礼": "cloudDisk",
  "辽宁_掌厅账单": "cloudDisk",
  "通用_掌厅账单": "cloudDisk",
  "全网_云化抽奖": "cloudDisk",
  "福建_摄影大赛": "cloudDisk",
  "上海活动数据推送": "",
  "天津_福利享不停活动": "",
  "江西_打工狂人": "cloudDisk",
  "江西_理想人设": "yunpage",
  "福建_月用月有礼": "fjllmfl",
  "湖北_会员好礼回馈": "yunpage",
  "甘肃_上传有礼": "",
  "甘肃_登录有礼": "cloudDisk",
  "云南_摄影大赛": "cloudDisk",
  "广东_订购页1元包": "gd4T2G",
  "广东_订购页2元包": "gd400G2G",
  "广东_订购页_2元包": "gd400G2G",
  "广东_订购页5元包": "gd1000G5G",
  "江西_最强人设活动": "yunpage",
  "上海_ 三重礼": "yunpage",

  "安徽_TV登录有礼": "",
  "吉林_TV登录有礼": "",
  "江西派奖逻辑优化": "",
  "江苏能开接口": "",
  "河南接口token缓存": "",
  "适配新底座": "",
  "上海推荐码数据推送": "",
  "福建自研活动接入领奖专区": "",
  "邀请码活动": "",
  "nan": "",
  "江西_新TV登录有礼": ""
}
